AppiumGuanfangWendangFix1/README.md
AppiumGuanfangWendangFix1/__init__.py
AppiumGuanfangWendangFix1/__main__.py
AppiumGuanfangWendangFix1/file.epub
AppiumGuanfangWendangFix1/index.html
AppiumGuanfangWendangFix1/css/__init__.py
AppiumGuanfangWendangFix1/css/annotations.css
AppiumGuanfangWendangFix1/css/main.css
AppiumGuanfangWendangFix1/css/normalize.css
AppiumGuanfangWendangFix1/css/popup.css
AppiumGuanfangWendangFix1/font/__init__.py
AppiumGuanfangWendangFix1/font/fontello.eot
AppiumGuanfangWendangFix1/font/fontello.svg
AppiumGuanfangWendangFix1/font/fontello.ttf
AppiumGuanfangWendangFix1/font/fontello.woff
AppiumGuanfangWendangFix1/img/__init__.py
AppiumGuanfangWendangFix1/img/annotator-glyph-sprite.png
AppiumGuanfangWendangFix1/img/annotator-icon-sprite.png
AppiumGuanfangWendangFix1/img/apple-touch-icon.png
AppiumGuanfangWendangFix1/img/cancelfullscreen.png
AppiumGuanfangWendangFix1/img/close.png
AppiumGuanfangWendangFix1/img/fullscreen.png
AppiumGuanfangWendangFix1/img/loader.gif
AppiumGuanfangWendangFix1/img/menu-icon.png
AppiumGuanfangWendangFix1/img/save.png
AppiumGuanfangWendangFix1/img/saved.png
AppiumGuanfangWendangFix1/img/settings-s.png
AppiumGuanfangWendangFix1/img/settings.png
AppiumGuanfangWendangFix1/img/star.png
AppiumGuanfangWendangFix1/js/__init__.py
AppiumGuanfangWendangFix1/js/epub.js
AppiumGuanfangWendangFix1/js/epub.min.js
AppiumGuanfangWendangFix1/js/epub.min.map
AppiumGuanfangWendangFix1/js/hooks.min.js
AppiumGuanfangWendangFix1/js/hooks.min.map
AppiumGuanfangWendangFix1/js/reader.js
AppiumGuanfangWendangFix1/js/reader.js.map
AppiumGuanfangWendangFix1/js/reader.min.js
AppiumGuanfangWendangFix1/js/reader.min.map
AppiumGuanfangWendangFix1/js/hooks/__init__.py
AppiumGuanfangWendangFix1/js/hooks/extensions/__init__.py
AppiumGuanfangWendangFix1/js/hooks/extensions/highlight.js
AppiumGuanfangWendangFix1/js/libs/__init__.py
AppiumGuanfangWendangFix1/js/libs/jquery.min.js
AppiumGuanfangWendangFix1/js/libs/localforage.min.js
appium_guanfang_wendang_fix1-2025.3.25.0.dist-info/METADATA
appium_guanfang_wendang_fix1-2025.3.25.0.dist-info/WHEEL
appium_guanfang_wendang_fix1-2025.3.25.0.dist-info/entry_points.txt
appium_guanfang_wendang_fix1-2025.3.25.0.dist-info/top_level.txt
appium_guanfang_wendang_fix1-2025.3.25.0.dist-info/RECORD
